imod2relion/__init__.py
imod2relion/_utils.py
imod2relion/main.py
imod2relion-1.1.0.dist-info/METADATA
imod2relion-1.1.0.dist-info/WHEEL
imod2relion-1.1.0.dist-info/entry_points.txt
imod2relion-1.1.0.dist-info/top_level.txt
imod2relion-1.1.0.dist-info/RECORD
