Metadata-Version: 2.1
Name: imod2relion
Version: 1.1.0
Summary: A tool reading IMOD points, obtaining particles' info and generating .star file for RELION
Home-page: https://github.com/ZhenHuangLab/imod2relion
Author: Zhen Huang
Author-email: hzvictor@zju.edu.cn
License: BSD 3-Clause License
Keywords: cryo-em,cryo-et,imod,relion,starfile
Requires-Python: >=3.9
Requires-Dist: starfile (>=0.4.11)
Requires-Dist: numpy (>=1.24.2)
Requires-Dist: pandas (>=1.5.3)
